<?xml version="1.0" encoding="GBK" ?>
<Data>
  <TestCase>
    <Bh>PPC003</Bh>
    <CaseName>冲红已存在的蓝票发票代码、号码，冲红成功</CaseName>
    <CaseId>51bs-2405</CaseId>
    <Description>冲红编号为PPC003的发票</Description>
    <Step id = "1">
      <Name>发票冲红</Name>
      <Keyword>IISSUE</Keyword>
      <DataList>PPC003</DataList>
      <TargetProject>CLOUD</TargetProject>
    </Step>
    <Step id = "2">
      <Name>是否冲红成功</Name>
      <Keyword>CHECK</Keyword>
      <DataList>PPC003check</DataList>
      <TargetDataList>PPC003</TargetDataList>
    </Step>
    <Step id = "3">
      <Name>发票查询</Name>
      <Keyword>IDETAIL</Keyword>
      <DataList>PPH003</DataList>
      <TargetProject>CLOUD</TargetProject>
    </Step>
    <Step id = "4">
      <Name>是否查询成功</Name>
      <Keyword>CHECK</Keyword>
      <DataList>PPH003check</DataList>
      <TargetDataList>PPH003</TargetDataList>
    </Step>
  </TestCase>

  <TestCase>
    <Bh>PPC004</Bh>
    <CaseName>冲红已存在的部分冲红蓝票发票代码、号码，冲红成功，税率0%</CaseName>
    <CaseId>51bs-2405</CaseId>
    <Description>冲红编号为PPC004的发票</Description>
    <Step id = "1">
      <Name>开票</Name>
      <Keyword>IISSUE</Keyword>
      <DataList>PPV001</DataList>
      <TargetProject>CLOUD</TargetProject>
    </Step>
    <Step id = "2">
      <Name>是否开具成功</Name>
      <Keyword>CHECK</Keyword>
      <DataList>PPCV004check</DataList>
      <TargetDataList>PPV001</TargetDataList>
    </Step>
    <Step id = "3">
      <Name>发票冲红</Name>
      <Keyword>IISSUE</Keyword>
      <DataList>PPC004</DataList>
      <TargetProject>CLOUD</TargetProject>
    </Step>
    <Step id = "4">
      <Name>是否冲红成功</Name>
      <Keyword>CHECK</Keyword>
      <DataList>PPC004check</DataList>
      <TargetDataList>PPC004</TargetDataList>
    </Step>
    <Step id = "5">
      <Name>发票查询</Name>
      <Keyword>IDETAIL</Keyword>
      <DataList>PPH004</DataList>
      <TargetProject>CLOUD</TargetProject>
    </Step>
    <Step id = "6">
      <Name>是否查询成功</Name>
      <Keyword>CHECK</Keyword>
      <DataList>PPH004check</DataList>
      <TargetDataList>PPH004</TargetDataList>
    </Step>
    <Step id = "7">
      <Name>发票冲红</Name>
      <Keyword>IISSUE</Keyword>
      <DataList>PPC004C</DataList>
      <TargetProject>CLOUD</TargetProject>
    </Step>
    <Step id = "8">
      <Name>是否冲红成功</Name>
      <Keyword>CHECK</Keyword>
      <DataList>PPC004Ccheck</DataList>
      <TargetDataList>PPC004C</TargetDataList>
    </Step>
    <Step id = "9">
      <Name>发票查询</Name>
      <Keyword>IDETAIL</Keyword>
      <DataList>PPH004C</DataList>
      <TargetProject>CLOUD</TargetProject>
    </Step>
    <Step id = "10">
      <Name>是否查询成功</Name>
      <Keyword>CHECK</Keyword>
      <DataList>PPH004Ccheck</DataList>
      <TargetDataList>PPH004C</TargetDataList>
    </Step>
  </TestCase>
  
   <TestCase>
    <Bh>PPC004a</Bh>
    <CaseName>冲红已存在的部分冲红蓝票发票代码、号码，冲红成功,税率3%</CaseName>
    <CaseId>51bs-2405</CaseId>
    <Description>冲红编号为PPC004a的发票</Description>
    <Step id = "1">
      <Name>开票</Name>
      <Keyword>IISSUE</Keyword>
      <DataList>PPV002</DataList>
      <TargetProject>CLOUD</TargetProject>
    </Step>
    <Step id = "2">
      <Name>是否开具成功</Name>
      <Keyword>CHECK</Keyword>
      <DataList>PPCKJcheck</DataList>
	   <TargetProject>CLOUD</TargetProject>
      <TargetDataList>PPV002</TargetDataList>
    </Step>
    <Step id = "3">
      <Name>发票冲红</Name>
      <Keyword>IISSUE</Keyword>
      <DataList>PPC004a</DataList>
      <TargetProject>CLOUD</TargetProject>
    </Step>
    <Step id = "4">
      <Name>是否冲红成功</Name>
      <Keyword>CHECK</Keyword>
      <DataList>PPCKJcheck</DataList>
      <TargetDataList>PPC004a</TargetDataList>
    </Step>
    <Step id = "5">
      <Name>发票查询</Name>
      <Keyword>IDETAIL</Keyword>
      <DataList>PPH004a</DataList>
      <TargetProject>CLOUD</TargetProject>
    </Step>
    <Step id = "6">
      <Name>是否查询成功</Name>
      <Keyword>CHECK</Keyword>
      <DataList>PPHCXcheck</DataList>
	     <TargetProject>CLOUD</TargetProject>
      <TargetDataList>PPH004a</TargetDataList>
    </Step>
    <Step id = "7">
      <Name>发票冲红</Name>
      <Keyword>IISSUE</Keyword>
      <DataList>PPC004aC</DataList>
      <TargetProject>CLOUD</TargetProject>
    </Step>
    <Step id = "8">
      <Name>是否冲红成功</Name>
      <Keyword>CHECK</Keyword>
        <DataList>PPCKJcheck</DataList>
	   <TargetProject>CLOUD</TargetProject>
      <TargetDataList>PPC004aC</TargetDataList>
    </Step>
    <Step id = "9">
      <Name>发票查询</Name>
      <Keyword>IDETAIL</Keyword>
      <DataList>PPH004aC</DataList>
      <TargetProject>CLOUD</TargetProject>
    </Step>
    <Step id = "10">
      <Name>是否查询成功</Name>
      <Keyword>CHECK</Keyword>
      <DataList>PPHCXcheck</DataList>
	     <TargetProject>CLOUD</TargetProject>
      <TargetDataList>PPH004aC</TargetDataList>
    </Step>
  </TestCase>

  <TestCase>
    <Bh>PPC005</Bh>
    <CaseName>冲红已作废未冲红的蓝票，冲红失败</CaseName>
    <CaseId>51bs-2405</CaseId>
    <Description>冲红编号为PPC005的发票</Description>
    <Step id = "1">
      <Name>开票</Name>
      <Keyword>IISSUE</Keyword>
      <DataList>PPV001</DataList>
      <TargetProject>CLOUD</TargetProject>
    </Step>
    <Step id = "2">
      <Name>是否开具成功</Name>
      <Keyword>CHECK</Keyword>
      <DataList>PPCV005check</DataList>
      <TargetProject>CLOUD</TargetProject>
    </Step>
    <Step id = "3">
      <Name>发票查询</Name>
      <Keyword>IDETAIL</Keyword>
      <DataList>PPH005</DataList>
      <TargetProject>CLOUD</TargetProject>
    </Step>
    <Step id = "4">
      <Name>作废发票</Name>
      <Keyword>IWASTE</Keyword>
      <DataList>PPFV005</DataList>
      <TargetProject>CLOUD</TargetProject>
    </Step>
    <Step id = "5">
      <Name>是否作废成功</Name>
      <Keyword>CHECK</Keyword>
      <DataList>PPFV005check</DataList>
      <TargetDataList>PPFV005</TargetDataList>
    </Step>
    
    <Step id = "6">
      <Name>发票冲红</Name>
      <Keyword>IISSUE</Keyword>
      <DataList>PPC005</DataList>
      <TargetProject>CLOUD</TargetProject>
    </Step>
    <Step id = "7">
      <Name>是否冲红成功</Name>
      <Keyword>CHECK</Keyword>
      <DataList>PPC005check</DataList>
      <TargetDataList>PPC005</TargetDataList>
    </Step>
  </TestCase>

  <TestCase>
    <Bh>PPC006</Bh>
    <CaseName>冲红蓝票未作废，有对应红票，红票全部作废，蓝票冲红成功</CaseName>
    <CaseId>51bs-2405</CaseId>
    <Description>冲红编号为PPC006的发票</Description>
    <Step id = "1">
      <Name>开票</Name>
      <Keyword>IISSUE</Keyword>
      <DataList>PPV001</DataList>
      <TargetProject>CLOUD</TargetProject>
    </Step>
    <Step id = "2">
      <Name>是否开具成功</Name>
      <Keyword>CHECK</Keyword>
      <DataList>PPCV006check</DataList>
      <TargetProject>CLOUD</TargetProject>
    </Step>
    <Step id = "3">
      <Name>发票查询</Name>
      <Keyword>IDETAIL</Keyword>
      <DataList>PPH006</DataList>
      <TargetProject>CLOUD</TargetProject>
    </Step>
    <Step id = "4">
      <Name>发票冲红</Name>
      <Keyword>IISSUE</Keyword>
      <DataList>PPC006</DataList>
      <TargetProject>CLOUD</TargetProject>
    </Step>
    <Step id = "5">
      <Name>是否冲红成功</Name>
      <Keyword>CHECK</Keyword>
      <DataList>PPC006check</DataList>
      <TargetDataList>PPC006</TargetDataList>
    </Step>
    <Step id = "6">
      <Name>发票查询</Name>
      <Keyword>IDETAIL</Keyword>
      <DataList>PPHC006</DataList>
      <TargetProject>CLOUD</TargetProject>
    </Step>
    <Step id = "7">
      <Name>作废发票</Name>
      <Keyword>IWASTE</Keyword>
      <DataList>PPFV006</DataList>
      <TargetProject>CLOUD</TargetProject>
    </Step>
    <Step id = "8">
      <Name>是否作废成功</Name>
      <Keyword>CHECK</Keyword>
      <DataList>PPFV006check</DataList>
      <TargetDataList>PPFV006</TargetDataList>
    </Step>
    <Step id = "9">
      <Name>发票冲红</Name>
      <Keyword>IISSUE</Keyword>
      <DataList>PPCC006</DataList>
      <TargetProject>CLOUD</TargetProject>
    </Step>
    <Step id = "10">
      <Name>是否冲红成功</Name>
      <Keyword>CHECK</Keyword>
      <DataList>PPCC006check</DataList>
      <TargetDataList>PPCC006</TargetDataList>
    </Step>
	    <Step id = "11">
      <Name>发票查询</Name>
      <Keyword>IDETAIL</Keyword>
      <DataList>PPCC006</DataList>
      <TargetProject>CLOUD</TargetProject>
    </Step>
    <Step id = "12">
      <Name>是否查询成功</Name>
      <Keyword>CHECK</Keyword>
      <DataList>PPH006Ccheck</DataList>
      <TargetDataList>PPCC006</TargetDataList>
    </Step>
 </TestCase>

  <TestCase>
    <Bh>PPC007</Bh>
    <CaseName>冲红蓝票未作废，有对应红票，作废部分红票，蓝票冲红成功</CaseName>
    <CaseId>51bs-2405</CaseId>
    <Description>冲红编号为PPC007的发票</Description>
    <Step id = "1">
      <Name>开票</Name>
      <Keyword>IISSUE</Keyword>
      <DataList>PPV001</DataList>
      <TargetProject>CLOUD</TargetProject>
    </Step>
    <Step id = "2">
      <Name>是否开具成功</Name>
      <Keyword>CHECK</Keyword>
      <DataList>PPCV007check</DataList>
      <TargetProject>CLOUD</TargetProject>
    </Step>
    <Step id = "3">
      <Name>发票查询</Name>
      <Keyword>IDETAIL</Keyword>
      <DataList>PPH007</DataList> 
      <TargetProject>CLOUD</TargetProject>
    </Step>
    <Step id = "4">
      <Name>发票冲红</Name>
      <Keyword>IISSUE</Keyword>
      <DataList>PPC007</DataList>
      <TargetProject>CLOUD</TargetProject>
    </Step>
    <Step id = "5">
      <Name>是否冲红成功</Name>
      <Keyword>CHECK</Keyword>
      <DataList>PPC007check</DataList>
      <TargetDataList>PPC007</TargetDataList>
    </Step>
    <Step id = "6">
      <Name>发票查询</Name>
      <Keyword>IDETAIL</Keyword>
      <DataList>PPHC007</DataList>
      <TargetProject>CLOUD</TargetProject>
    </Step>
    <Step id = "7">
      <Name>发票冲红</Name>
      <Keyword>IISSUE</Keyword>
      <DataList>PPCC007</DataList>
      <TargetProject>CLOUD</TargetProject>
    </Step>
    <Step id = "8">
      <Name>是否冲红成功</Name>
      <Keyword>CHECK</Keyword>
      <DataList>PPCC007check</DataList>
      <TargetDataList>PPCC007</TargetDataList>
    </Step>
    <!--<Step id = "9">
      <Name>发票查询</Name>
      <Keyword>IDETAIL</Keyword>
      <DataList>PPHCC007</DataList>
      <TargetProject>CLOUD</TargetProject>
    </Step>-->
    <Step id = "10">
      <Name>作废发票</Name>
      <Keyword>IWASTE</Keyword>
      <DataList>PPCC007</DataList>
      <TargetProject>CLOUD</TargetProject>
    </Step>
    <Step id = "11">
      <Name>是否作废成功</Name>
      <Keyword>CHECK</Keyword>
      <DataList>PPFV007check</DataList>
      <TargetDataList>PPCC007</TargetDataList>
    </Step>
    <Step id = "12">
      <Name>发票冲红</Name>
      <Keyword>IISSUE</Keyword>
      <DataList>PPCCC007</DataList>
      <TargetProject>CLOUD</TargetProject>
    </Step>
    <Step id = "13">
      <Name>是否冲红成功</Name>
      <Keyword>CHECK</Keyword>
      <DataList>PPCCC007check</DataList>
      <TargetDataList>PPCCC007</TargetDataList>
    </Step>
  </TestCase>
  
  <TestCase>
    <Bh>PPC008</Bh>
    <CaseName>冲红蓝票未作废，有对应红票，再次冲红金额大于剩余冲红金额，冲红失败</CaseName>
    <CaseId>51bs-2405</CaseId>
    <Description>冲红编号为PPC008的发票</Description>
    <Step id = "1">
      <Name>开票</Name>
      <Keyword>IISSUE</Keyword>
      <DataList>PPV001</DataList>
      <TargetProject>CLOUD</TargetProject>
    </Step>
    <Step id = "2">
      <Name>是否开具成功</Name>
      <Keyword>CHECK</Keyword>
      <DataList>PPCV008check</DataList>
      <TargetProject>CLOUD</TargetProject>
    </Step>
    <Step id = "3">
      <Name>发票查询</Name>
      <Keyword>IDETAIL</Keyword>
      <DataList>PPH008</DataList>
      <TargetProject>CLOUD</TargetProject>
    </Step>
    <Step id = "4">
      <Name>发票冲红</Name>
      <Keyword>IISSUE</Keyword>
      <DataList>PPC008</DataList>
      <TargetProject>CLOUD</TargetProject>
    </Step>
    <Step id = "5">
      <Name>是否冲红成功</Name>
      <Keyword>CHECK</Keyword>
      <DataList>PPC008check</DataList>
      <TargetDataList>PPC008</TargetDataList>
    </Step>
    <Step id = "6">
      <Name>发票查询</Name>
      <Keyword>IDETAIL</Keyword>
      <DataList>PPHC008</DataList>
      <TargetProject>CLOUD</TargetProject>
    </Step>
    <Step id = "7">
      <Name>发票冲红</Name>
      <Keyword>IISSUE</Keyword>
      <DataList>PPCC008</DataList>
      <TargetProject>CLOUD</TargetProject>
    </Step>
    <Step id = "8">
      <Name>是否冲红成功</Name>
      <Keyword>CHECK</Keyword>
      <DataList>PPCC008check</DataList>
      <TargetDataList>PPCC008</TargetDataList>
    </Step>
 </TestCase>
  
  
  <TestCase>
    <Bh>PPC009</Bh>
    <CaseName>部分冲红单税率单行发票- 普通0税率发票</CaseName>
      <CaseId>51bs-2406</CaseId>
    <Description>冲红编号为PPC009的发票</Description>
    <Step id = "1">
      <Name>开票</Name>
      <Keyword>IISSUE</Keyword>
      <DataList>PPV001</DataList>
      <TargetProject>CLOUD</TargetProject>
    </Step>
    <Step id = "2">
      <Name>是否开具成功</Name>
      <Keyword>CHECK</Keyword>
      <DataList>PPC009check</DataList>
      <TargetProject>CLOUD</TargetProject>
    </Step>
    <Step id = "3">
      <Name>发票冲红</Name>
      <Keyword>IISSUE</Keyword>
      <DataList>PPC009</DataList>
      <TargetProject>CLOUD</TargetProject>
    </Step>
    <Step id = "4">
      <Name>是否冲红成功</Name>
      <Keyword>CHECK</Keyword>
      <DataList>PPC009check</DataList>
      <TargetDataList>PPC009</TargetDataList>
    </Step>
    <Step id = "5">
      <Name>发票查询</Name>
      <Keyword>IDETAIL</Keyword>
      <DataList>PPH009</DataList>
      <TargetProject>CLOUD</TargetProject>
    </Step>
    <Step id = "6">
      <Name>是否查询成功</Name>
      <Keyword>CHECK</Keyword>
      <DataList>PPH009check</DataList>
      <TargetDataList>PPH009</TargetDataList>
    </Step>
    <Step id = "7">
      <Name>查询结果比对</Name>
      <Keyword>CHECK</Keyword>
      <DataList>PPG009check</DataList>
    </Step>
  </TestCase>

  <TestCase>
    <Bh>PPC010</Bh>
    <CaseName>部分冲红单税率单行发票- 免税税率发票</CaseName>
    <CaseId>51bs-2406</CaseId>
    <Description>冲红编号为PPC010的发票</Description>
    <Step id = "1">
      <Name>开票</Name>
      <Keyword>IISSUE</Keyword>
      <DataList>PPV009</DataList>
      <TargetProject>CLOUD</TargetProject>
    </Step>
    <Step id = "2">
      <Name>是否开具成功</Name>
      <Keyword>CHECK</Keyword>
      <DataList>PPC010check</DataList>
      <TargetProject>CLOUD</TargetProject>
    </Step>
    <Step id = "3">
      <Name>发票冲红</Name>
      <Keyword>IISSUE</Keyword>
      <DataList>PPC010</DataList>
      <TargetProject>CLOUD</TargetProject>
    </Step>
    <Step id = "4">
      <Name>是否冲红成功</Name>
      <Keyword>CHECK</Keyword>
      <DataList>PPC010check</DataList>
      <TargetDataList>PPC010</TargetDataList>
    </Step>
    <Step id = "5">
      <Name>发票查询</Name>
      <Keyword>IDETAIL</Keyword>
      <DataList>PPH010</DataList>
      <TargetProject>CLOUD</TargetProject>
    </Step>
    <Step id = "6">
      <Name>是否查询成功</Name>
      <Keyword>CHECK</Keyword>
      <DataList>PPH010check</DataList>
      <TargetDataList>PPH010</TargetDataList>
    </Step>
    <Step id = "7">
      <Name>查询结果比对</Name>
      <Keyword>CHECK</Keyword>
      <DataList>PPG010check</DataList>
    </Step>
  </TestCase>

  <TestCase>
    <Bh>PPC011</Bh>
    <CaseName>部分冲红单税率单行发票- 不征税税率发票</CaseName>
    <CaseId>51bs-2406</CaseId>
    <Description>冲红编号为PPC011的发票</Description>
    <Step id = "1">
      <Name>开票</Name>
      <Keyword>IISSUE</Keyword>
      <DataList>PPV010</DataList>
      <TargetProject>CLOUD</TargetProject>
    </Step>
    <Step id = "2">
      <Name>是否开具成功</Name>
      <Keyword>CHECK</Keyword>
      <DataList>PPC011check</DataList>
      <TargetProject>CLOUD</TargetProject>
    </Step>
    <Step id = "3">
      <Name>发票冲红</Name>
      <Keyword>IISSUE</Keyword>
      <DataList>PPC011</DataList>
      <TargetProject>CLOUD</TargetProject>
    </Step>
    <Step id = "4">
      <Name>是否冲红成功</Name>
      <Keyword>CHECK</Keyword>
      <DataList>PPC011check</DataList>
      <TargetDataList>PPC011</TargetDataList>
    </Step>
    <Step id = "5">
      <Name>发票查询</Name>
      <Keyword>IDETAIL</Keyword>
      <DataList>PPH011</DataList>
      <TargetProject>CLOUD</TargetProject>
    </Step>
    <Step id = "6">
      <Name>是否查询成功</Name>
      <Keyword>CHECK</Keyword>
      <DataList>PPH011check</DataList>
      <TargetDataList>PPH011</TargetDataList>
    </Step>
    <Step id = "7">
      <Name>查询结果比对</Name>
      <Keyword>CHECK</Keyword>
      <DataList>PPG011check</DataList>
    </Step>
  </TestCase>
  
  
    <TestCase>
      <Bh>PPC012</Bh>
      <CaseName>部分冲红单税率单行发票- 普通3%税率发票</CaseName>
      <CaseId>51bs-2406</CaseId>
      <Description>冲红编号为PPC012的发票</Description>
      <Step id = "1">
        <Name>开票</Name>
        <Keyword>IISSUE</Keyword>
        <DataList>PPV002</DataList>
        <TargetProject>CLOUD</TargetProject>
      </Step>
      <Step id = "2">
        <Name>是否开具成功</Name>
        <Keyword>CHECK</Keyword>
        <DataList>PPC012check</DataList>
        <TargetProject>CLOUD</TargetProject>
      </Step>
      <Step id = "3">
        <Name>发票冲红</Name>
        <Keyword>IISSUE</Keyword>
        <DataList>PPC012</DataList>
        <TargetProject>CLOUD</TargetProject>
      </Step>
      <Step id = "4">
        <Name>是否冲红成功</Name>
        <Keyword>CHECK</Keyword>
        <DataList>PPC012check</DataList>
        <TargetDataList>PPC012</TargetDataList>
      </Step>
      <Step id = "5">
        <Name>发票查询</Name>
        <Keyword>IDETAIL</Keyword>
        <DataList>PPH012</DataList>
        <TargetProject>CLOUD</TargetProject>
      </Step>
      <Step id = "6">
        <Name>是否查询成功</Name>
        <Keyword>CHECK</Keyword>
        <DataList>PPH012check</DataList>
        <TargetDataList>PPH012</TargetDataList>
      </Step>
      <Step id = "7">
        <Name>查询结果比对</Name>
        <Keyword>CHECK</Keyword>
        <DataList>PPG012check</DataList>
      </Step>
  </TestCase>

  <TestCase>
    <Bh>PPC013</Bh>
    <CaseName>部分冲红单税率3行发票- 普通0税率发票</CaseName>
    <CaseId>51bs-2406</CaseId>
    <Description>冲红编号为PPC013的发票</Description>
    <Step id = "1">
      <Name>开票</Name>
      <Keyword>IISSUE</Keyword>
      <DataList>PPV011</DataList>
      <TargetProject>CLOUD</TargetProject>
    </Step>
    <Step id = "2">
      <Name>是否开具成功</Name>
      <Keyword>CHECK</Keyword>
      <DataList>PPC013check</DataList>
      <TargetProject>CLOUD</TargetProject>
    </Step>
    <Step id = "3">
      <Name>发票冲红</Name>
      <Keyword>IISSUE</Keyword>
      <DataList>PPC013</DataList>
      <TargetProject>CLOUD</TargetProject>
    </Step>
    <Step id = "4">
      <Name>是否冲红成功</Name>
      <Keyword>CHECK</Keyword>
      <DataList>PPC013check</DataList>
      <TargetDataList>PPC013</TargetDataList>
    </Step>
    <Step id = "5">
      <Name>发票查询</Name>
      <Keyword>IDETAIL</Keyword>
      <DataList>PPH013</DataList>
      <TargetProject>CLOUD</TargetProject>
    </Step>
    <Step id = "6">
      <Name>是否查询成功</Name>
      <Keyword>CHECK</Keyword>
      <DataList>PPH013check</DataList>
      <TargetDataList>PPH013</TargetDataList>
    </Step>
    <Step id = "7">
      <Name>查询结果比对</Name>
      <Keyword>CHECK</Keyword>
      <DataList>PPG013check</DataList>
    </Step>
  </TestCase>

  <TestCase>
    <Bh>PPC014</Bh>
    <CaseName>部分冲红单税率3行发票- 免税税率发票</CaseName>
    <CaseId>51bs-2406</CaseId>
    <Description>冲红编号为PPC014的发票</Description>
    <Step id = "1">
      <Name>开票</Name>
      <Keyword>IISSUE</Keyword>
      <DataList>PPV019</DataList>
      <TargetProject>CLOUD</TargetProject>
    </Step>
    <Step id = "2">
      <Name>是否开具成功</Name>
      <Keyword>CHECK</Keyword>
      <DataList>PPC014check</DataList>
      <TargetProject>CLOUD</TargetProject>
    </Step>
    <Step id = "3">
      <Name>发票冲红</Name>
      <Keyword>IISSUE</Keyword>
      <DataList>PPC014</DataList>
      <TargetProject>CLOUD</TargetProject>
    </Step>
    <Step id = "4">
      <Name>是否冲红成功</Name>
      <Keyword>CHECK</Keyword>
      <DataList>PPC014check</DataList>
      <TargetDataList>PPC014</TargetDataList>
    </Step>
    <Step id = "5">
      <Name>发票查询</Name>
      <Keyword>IDETAIL</Keyword>
      <DataList>PPH014</DataList>
      <TargetProject>CLOUD</TargetProject>
    </Step>
    <Step id = "6">
      <Name>是否查询成功</Name>
      <Keyword>CHECK</Keyword>
      <DataList>PPH014check</DataList>
      <TargetDataList>PPH014</TargetDataList>
    </Step>
    <Step id = "7">
      <Name>查询结果比对</Name>
      <Keyword>CHECK</Keyword>
      <DataList>PPG014check</DataList>
    </Step>
  </TestCase>

  <TestCase>
    <Bh>PPC015</Bh>
    <CaseName>部分冲红单税率3行发票- 不征税税率发票</CaseName>
    <CaseId>51bs-2406</CaseId>
    <Description>冲红编号为PPC015的发票</Description>
    <Step id = "1">
      <Name>开票</Name>
      <Keyword>IISSUE</Keyword>
      <DataList>PPV020</DataList>
      <TargetProject>CLOUD</TargetProject>
    </Step>
    <Step id = "2">
      <Name>是否开具成功</Name>
      <Keyword>CHECK</Keyword>
      <DataList>PPC015check</DataList>
      <TargetProject>CLOUD</TargetProject>
    </Step>
    <Step id = "3">
      <Name>发票冲红</Name>
      <Keyword>IISSUE</Keyword>
      <DataList>PPC015</DataList>
      <TargetProject>CLOUD</TargetProject>
    </Step>
    <Step id = "4">
      <Name>是否冲红成功</Name>
      <Keyword>CHECK</Keyword>
      <DataList>PPC015check</DataList>
      <TargetDataList>PPC015</TargetDataList>
    </Step>
    <Step id = "5">
      <Name>发票查询</Name>
      <Keyword>IDETAIL</Keyword>
      <DataList>PPH015</DataList>
      <TargetProject>CLOUD</TargetProject>
    </Step>
    <Step id = "6">
      <Name>是否查询成功</Name>
      <Keyword>CHECK</Keyword>
      <DataList>PPH015check</DataList>
      <TargetDataList>PPH015</TargetDataList>
    </Step>
    <Step id = "7">
      <Name>查询结果比对</Name>
      <Keyword>CHECK</Keyword>
      <DataList>PPG015check</DataList>
    </Step>
  </TestCase>
  
  <TestCase>
    <Bh>PPC016</Bh>
    <CaseName>部分冲红单税率3行发票- 普通6%税率发票</CaseName>
    <CaseId>51bs-2406</CaseId>
    <Description>冲红编号为PPC016的发票</Description>
    <Step id = "1">
      <Name>开票</Name>
      <Keyword>IISSUE</Keyword>
      <DataList>PPV015</DataList>
      <TargetProject>CLOUD</TargetProject>
    </Step>
    <Step id = "2">
      <Name>是否开具成功</Name>
      <Keyword>CHECK</Keyword>
      <DataList>PPC016check</DataList>
      <TargetProject>CLOUD</TargetProject>
    </Step>
    <Step id = "3">
      <Name>发票冲红</Name>
      <Keyword>IISSUE</Keyword>
      <DataList>PPC016</DataList>
      <TargetProject>CLOUD</TargetProject>
    </Step>
    <Step id = "4">
      <Name>是否冲红成功</Name>
      <Keyword>CHECK</Keyword>
      <DataList>PPC016check</DataList>
      <TargetDataList>PPC016</TargetDataList>
    </Step>
    <Step id = "5">
      <Name>发票查询</Name>
      <Keyword>IDETAIL</Keyword>
      <DataList>PPH016</DataList>
      <TargetProject>CLOUD</TargetProject>
    </Step>
    <Step id = "6">
      <Name>是否查询成功</Name>
      <Keyword>CHECK</Keyword>
      <DataList>PPH016check</DataList>
      <TargetDataList>PPH016</TargetDataList>
    </Step>
    <Step id = "7">
      <Name>查询结果比对</Name>
      <Keyword>CHECK</Keyword>
      <DataList>PPG016check</DataList>
    </Step>
  </TestCase>

  <TestCase>
    <Bh>PPC017</Bh>
    <CaseName>部分冲红多税率3行发票- 11%-13%-17%税率发票</CaseName>
    <CaseId>51bs-2406</CaseId>
    <Description>冲红编号为PPC017的发票</Description>
    <Step id = "1">
      <Name>开票</Name>
      <Keyword>IISSUE</Keyword>
      <DataList>PPV021</DataList>
      <TargetProject>CLOUD</TargetProject>
    </Step>
    <Step id = "2">
      <Name>是否开具成功</Name>
      <Keyword>CHECK</Keyword>
      <DataList>PPC017check</DataList>
      <TargetProject>CLOUD</TargetProject>
    </Step>
    <Step id = "3">
      <Name>发票冲红</Name>
      <Keyword>IISSUE</Keyword>
      <DataList>PPC017</DataList>
      <TargetProject>CLOUD</TargetProject>
    </Step>
    <Step id = "4">
      <Name>是否冲红成功</Name>
      <Keyword>CHECK</Keyword>
      <DataList>PPC017check</DataList>
      <TargetDataList>PPC017</TargetDataList>
    </Step>
    <Step id = "5">
      <Name>发票查询</Name>
      <Keyword>IDETAIL</Keyword>
      <DataList>PPH017</DataList>
      <TargetProject>CLOUD</TargetProject>
    </Step>
    <Step id = "6">
      <Name>是否查询成功</Name>
      <Keyword>CHECK</Keyword>
      <DataList>PPH017check</DataList>
      <TargetDataList>PPH017</TargetDataList>
    </Step>
    <Step id = "7">
      <Name>查询结果比对</Name>
      <Keyword>CHECK</Keyword>
      <DataList>PPG017check</DataList>
    </Step>
  </TestCase>

  <TestCase>
    <Bh>PPC018</Bh>
    <CaseName>部分冲红多税率3行发票- 0%-4%-5%税率发票</CaseName>
    <CaseId>51bs-2406</CaseId>
    <Description>冲红编号为PPC018的发票</Description>
    <Step id = "1">
      <Name>开票</Name>
      <Keyword>IISSUE</Keyword>
      <DataList>PPV022</DataList>
      <TargetProject>CLOUD</TargetProject>
    </Step>
    <Step id = "2">
      <Name>是否开具成功</Name>
      <Keyword>CHECK</Keyword>
      <DataList>PPC018check</DataList>
      <TargetProject>CLOUD</TargetProject>
    </Step>
    <Step id = "3">
      <Name>发票冲红</Name>
      <Keyword>IISSUE</Keyword>
      <DataList>PPC018</DataList>
      <TargetProject>CLOUD</TargetProject>
    </Step>
    <Step id = "4">
      <Name>是否冲红成功</Name>
      <Keyword>CHECK</Keyword>
      <DataList>PPC018check</DataList>
      <TargetDataList>PPC018</TargetDataList>
    </Step>
    <Step id = "5">
      <Name>发票查询</Name>
      <Keyword>IDETAIL</Keyword>
      <DataList>PPH018</DataList>
      <TargetProject>CLOUD</TargetProject>
    </Step>
    <Step id = "6">
      <Name>是否查询成功</Name>
      <Keyword>CHECK</Keyword>
      <DataList>PPH018check</DataList>
      <TargetDataList>PPH018</TargetDataList>
    </Step>
    <Step id = "7">
      <Name>查询结果比对</Name>
      <Keyword>CHECK</Keyword>
      <DataList>PPG018check</DataList>
    </Step>
  </TestCase>

  <TestCase>
    <Bh>PPC019</Bh>
    <CaseName>部分冲红多税率3行发票-6%-11%-13%税率发票</CaseName>
    <CaseId>51bs-2406</CaseId>
    <Description>冲红编号为PPC019的发票</Description>
    <Step id = "1">
      <Name>开票</Name>
      <Keyword>IISSUE</Keyword>
      <DataList>PPV023</DataList>
      <TargetProject>CLOUD</TargetProject>
    </Step>
    <Step id = "2">
      <Name>是否开具成功</Name>
      <Keyword>CHECK</Keyword>
      <DataList>PPC019check</DataList>
      <TargetProject>CLOUD</TargetProject>
    </Step>
    <Step id = "3">
      <Name>发票冲红</Name>
      <Keyword>IISSUE</Keyword>
      <DataList>PPC019</DataList>
      <TargetProject>CLOUD</TargetProject>
    </Step>
    <Step id = "4">
      <Name>是否冲红成功</Name>
      <Keyword>CHECK</Keyword>
      <DataList>PPC019check</DataList>
      <TargetDataList>PPC019</TargetDataList>
    </Step>
    <Step id = "5">
      <Name>发票查询</Name>
      <Keyword>IDETAIL</Keyword>
      <DataList>PPH019</DataList>
      <TargetProject>CLOUD</TargetProject>
    </Step>
    <Step id = "6">
      <Name>是否查询成功</Name>
      <Keyword>CHECK</Keyword>
      <DataList>PPH019check</DataList>
      <TargetDataList>PPH019</TargetDataList>
    </Step>
    <Step id = "7">
      <Name>查询结果比对</Name>
      <Keyword>CHECK</Keyword>
      <DataList>PPG019check</DataList>
    </Step>
  </TestCase>

  <TestCase>
    <Bh>PPC020</Bh>
    <CaseName>部分冲红多税率3行发票-0%-11%-13%税率发票</CaseName>
    <CaseId>51bs-2406</CaseId>
    <Description>冲红编号为PPC020的发票</Description>
    <Step id = "1">
      <Name>开票</Name>
      <Keyword>IISSUE</Keyword>
      <DataList>PPV024</DataList>
      <TargetProject>CLOUD</TargetProject>
    </Step>
    <Step id = "2">
      <Name>是否开具成功</Name>
      <Keyword>CHECK</Keyword>
      <DataList>PPC020check</DataList>
      <TargetProject>CLOUD</TargetProject>
    </Step>
    <Step id = "3">
      <Name>发票冲红</Name>
      <Keyword>IISSUE</Keyword>
      <DataList>PPC020</DataList>
      <TargetProject>CLOUD</TargetProject>
    </Step>
    <Step id = "4">
      <Name>是否冲红成功</Name>
      <Keyword>CHECK</Keyword>
      <DataList>PPC020check</DataList>
      <TargetDataList>PPC020</TargetDataList>
    </Step>
    <Step id = "5">
      <Name>发票查询</Name>
      <Keyword>IDETAIL</Keyword>
      <DataList>PPH020</DataList>
      <TargetProject>CLOUD</TargetProject>
    </Step>
    <Step id = "6">
      <Name>是否查询成功</Name>
      <Keyword>CHECK</Keyword>
      <DataList>PPH020check</DataList>
      <TargetDataList>PPH020</TargetDataList>
    </Step>
    <Step id = "7">
      <Name>查询结果比对</Name>
      <Keyword>CHECK</Keyword>
      <DataList>PPG020check</DataList>
    </Step>
  </TestCase>

  <TestCase>
    <Bh>PPC021</Bh>
    <CaseName>部分冲红非清单8行单税率-0税率发票</CaseName>
    <CaseId>51bs-2406</CaseId>
    <Description>冲红编号为PPC021的发票</Description>
    <Step id = "1">
      <Name>开票</Name>
      <Keyword>IISSUE</Keyword>
      <DataList>PPV025</DataList>
      <TargetProject>CLOUD</TargetProject>
    </Step>
    <Step id = "2">
      <Name>是否开具成功</Name>
      <Keyword>CHECK</Keyword>
      <DataList>PPC021check</DataList>
      <TargetProject>CLOUD</TargetProject>
    </Step>
    <Step id = "3">
      <Name>发票冲红</Name>
      <Keyword>IISSUE</Keyword>
      <DataList>PPC021</DataList>
      <TargetProject>CLOUD</TargetProject>
    </Step>
    <Step id = "4">
      <Name>是否冲红成功</Name>
      <Keyword>CHECK</Keyword>
      <DataList>PPC021check</DataList>
      <TargetDataList>PPC021</TargetDataList>
    </Step>
    <Step id = "5">
      <Name>发票查询</Name>
      <Keyword>IDETAIL</Keyword>
      <DataList>PPH021</DataList>
      <TargetProject>CLOUD</TargetProject>
    </Step>
    <Step id = "6">
      <Name>是否查询成功</Name>
      <Keyword>CHECK</Keyword>
      <DataList>PPH021check</DataList>
      <TargetDataList>PPH021</TargetDataList>
    </Step>
    <Step id = "7">
      <Name>查询结果比对</Name>
      <Keyword>CHECK</Keyword>
      <DataList>PPG021check</DataList>
    </Step>
  </TestCase>

  <TestCase>
    <Bh>PPC022</Bh>
    <CaseName>部分冲红非清单8行单税率-免税税率发票</CaseName>
    <CaseId>51bs-2406</CaseId>
    <Description>冲红编号为PPC022的发票</Description>
    <Step id = "1">
      <Name>开票</Name>
      <Keyword>IISSUE</Keyword>
      <DataList>PPV027</DataList>
      <TargetProject>CLOUD</TargetProject>
    </Step>
    <Step id = "2">
      <Name>是否开具成功</Name>
      <Keyword>CHECK</Keyword>
      <DataList>PPC022check</DataList>
      <TargetProject>CLOUD</TargetProject>
    </Step>
    <Step id = "3">
      <Name>发票冲红</Name>
      <Keyword>IISSUE</Keyword>
      <DataList>PPC022</DataList>
      <TargetProject>CLOUD</TargetProject>
    </Step>
    <Step id = "4">
      <Name>是否冲红成功</Name>
      <Keyword>CHECK</Keyword>
      <DataList>PPC022check</DataList>
      <TargetDataList>PPC022</TargetDataList>
    </Step>
    <Step id = "5">
      <Name>发票查询</Name>
      <Keyword>IDETAIL</Keyword>
      <DataList>PPH022</DataList>
      <TargetProject>CLOUD</TargetProject>
    </Step>
    <Step id = "6">
      <Name>是否查询成功</Name>
      <Keyword>CHECK</Keyword>
      <DataList>PPH022check</DataList>
      <TargetDataList>PPH022</TargetDataList>
    </Step>
    <Step id = "7">
      <Name>查询结果比对</Name>
      <Keyword>CHECK</Keyword>
      <DataList>PPG022check</DataList>
    </Step>
  </TestCase>

  <TestCase>
    <Bh>PPC023</Bh>
    <CaseName>部分冲红非清单8行单税率-不征税税率发票</CaseName>
    <CaseId>51bs-2406</CaseId>
    <Description>冲红编号为PPC023的发票</Description>
    <Step id = "1">
      <Name>开票</Name>
      <Keyword>IISSUE</Keyword>
      <DataList>PPV028</DataList>
      <TargetProject>CLOUD</TargetProject>
    </Step>
    <Step id = "2">
      <Name>是否开具成功</Name>
      <Keyword>CHECK</Keyword>
      <DataList>PPC023check</DataList>
      <TargetProject>CLOUD</TargetProject>
    </Step>
    <Step id = "3">
      <Name>发票冲红</Name>
      <Keyword>IISSUE</Keyword>
      <DataList>PPC023</DataList>
      <TargetProject>CLOUD</TargetProject>
    </Step>
    <Step id = "4">
      <Name>是否冲红成功</Name>
      <Keyword>CHECK</Keyword>
      <DataList>PPC023check</DataList>
      <TargetDataList>PPC023</TargetDataList>
    </Step>
    <Step id = "5">
      <Name>发票查询</Name>
      <Keyword>IDETAIL</Keyword>
      <DataList>PPH023</DataList>
      <TargetProject>CLOUD</TargetProject>
    </Step>
    <Step id = "6">
      <Name>是否查询成功</Name>
      <Keyword>CHECK</Keyword>
      <DataList>PPH023check</DataList>
      <TargetDataList>PPH023</TargetDataList>
    </Step>
    <Step id = "7">
      <Name>查询结果比对</Name>
      <Keyword>CHECK</Keyword>
      <DataList>PPG023check</DataList>
    </Step>
  </TestCase>

  <TestCase>
    <Bh>PPC024</Bh>
    <CaseName>部分冲红非清单8行单税率-普通3%税率发票</CaseName>
    <CaseId>51bs-2406</CaseId>
    <Description>冲红编号为PPC024的发票</Description>
    <Step id = "1">
      <Name>开票</Name>
      <Keyword>IISSUE</Keyword>
      <DataList>PPV026</DataList>
      <TargetProject>CLOUD</TargetProject>
    </Step>
    <Step id = "2">
      <Name>是否开具成功</Name>
      <Keyword>CHECK</Keyword>
      <DataList>PPC024check</DataList>
      <TargetProject>CLOUD</TargetProject>
    </Step>
    <Step id = "3">
      <Name>发票冲红</Name>
      <Keyword>IISSUE</Keyword>
      <DataList>PPC024</DataList>
      <TargetProject>CLOUD</TargetProject>
    </Step>
    <Step id = "4">
      <Name>是否冲红成功</Name>
      <Keyword>CHECK</Keyword>
      <DataList>PPC024check</DataList>
      <TargetDataList>PPC024</TargetDataList>
    </Step>
    <Step id = "5">
      <Name>发票查询</Name>
      <Keyword>IDETAIL</Keyword>
      <DataList>PPH024</DataList>
      <TargetProject>CLOUD</TargetProject>
    </Step>
    <Step id = "6">
      <Name>是否查询成功</Name>
      <Keyword>CHECK</Keyword>
      <DataList>PPH024check</DataList>
      <TargetDataList>PPH024</TargetDataList>
    </Step>
    <Step id = "7">
      <Name>查询结果比对</Name>
      <Keyword>CHECK</Keyword>
      <DataList>PPG024check</DataList>
    </Step>
  </TestCase>

  <TestCase>
    <Bh>PPC025</Bh>
    <CaseName>部分冲红非清单8行多税率-0税率与普通税率发票</CaseName>
    <CaseId>51bs-2406</CaseId>
    <Description>冲红编号为PPC025的发票</Description>
    <Step id = "1">
      <Name>开票</Name>
      <Keyword>IISSUE</Keyword>
      <DataList>PPV032</DataList>
      <TargetProject>CLOUD</TargetProject>
    </Step>
    <Step id = "2">
      <Name>是否开具成功</Name>
      <Keyword>CHECK</Keyword>
      <DataList>PPC025check</DataList>
      <TargetProject>CLOUD</TargetProject>
    </Step>
    <Step id = "3">
      <Name>发票冲红</Name>
      <Keyword>IISSUE</Keyword>
      <DataList>PPC025</DataList>
      <TargetProject>CLOUD</TargetProject>
    </Step>
    <Step id = "4">
      <Name>是否冲红成功</Name>
      <Keyword>CHECK</Keyword>
      <DataList>PPC025check</DataList>
      <TargetDataList>PPC025</TargetDataList>
    </Step>
    <Step id = "5">
      <Name>发票查询</Name>
      <Keyword>IDETAIL</Keyword>
      <DataList>PPH025</DataList>
      <TargetProject>CLOUD</TargetProject>
    </Step>
    <Step id = "6">
      <Name>是否查询成功</Name>
      <Keyword>CHECK</Keyword>
      <DataList>PPH025check</DataList>
      <TargetDataList>PPH025</TargetDataList>
    </Step>
    <Step id = "7">
      <Name>查询结果比对</Name>
      <Keyword>CHECK</Keyword>
      <DataList>PPG025check</DataList>
    </Step>
  </TestCase>

  <TestCase>
    <Bh>PPC026</Bh>
    <CaseName>部分冲红非清单8行多税率-免税率与普通税率发票</CaseName>
    <CaseId>51bs-2406</CaseId>
    <Description>冲红编号为PPC026的发票</Description>
    <Step id = "1">
      <Name>开票</Name>
      <Keyword>IISSUE</Keyword>
      <DataList>PPV034</DataList>
      <TargetProject>CLOUD</TargetProject>
    </Step>
    <Step id = "2">
      <Name>是否开具成功</Name>
      <Keyword>CHECK</Keyword>
      <DataList>PPC026check</DataList>
      <TargetProject>CLOUD</TargetProject>
    </Step>
    <Step id = "3">
      <Name>发票冲红</Name>
      <Keyword>IISSUE</Keyword>
      <DataList>PPC026</DataList>
      <TargetProject>CLOUD</TargetProject>
    </Step>
    <Step id = "4">
      <Name>是否冲红成功</Name>
      <Keyword>CHECK</Keyword>
      <DataList>PPC026check</DataList>
      <TargetDataList>PPC026</TargetDataList>
    </Step>
    <Step id = "5">
      <Name>发票查询</Name>
      <Keyword>IDETAIL</Keyword>
      <DataList>PPH026</DataList>
      <TargetProject>CLOUD</TargetProject>
    </Step>
    <Step id = "6">
      <Name>是否查询成功</Name>
      <Keyword>CHECK</Keyword>
      <DataList>PPH026check</DataList>
      <TargetDataList>PPH026</TargetDataList>
    </Step>
    <Step id = "7">
      <Name>查询结果比对</Name>
      <Keyword>CHECK</Keyword>
      <DataList>PPG026check</DataList>
    </Step>
  </TestCase>

  <TestCase>
    <Bh>PPC027</Bh>
    <CaseName>部分冲红非清单8行多税率-不征税率与普通税率发票</CaseName>
    <CaseId>51bs-2406</CaseId>
    <Description>冲红编号为PPC027的发票</Description>
    <Step id = "1">
      <Name>开票</Name>
      <Keyword>IISSUE</Keyword>
      <DataList>PPV035</DataList>
      <TargetProject>CLOUD</TargetProject>
    </Step>
    <Step id = "2">
      <Name>是否开具成功</Name>
      <Keyword>CHECK</Keyword>
      <DataList>PPC027check</DataList>
      <TargetProject>CLOUD</TargetProject>
    </Step>
    <Step id = "3">
      <Name>发票冲红</Name>
      <Keyword>IISSUE</Keyword>
      <DataList>PPC027</DataList>
      <TargetProject>CLOUD</TargetProject>
    </Step>
    <Step id = "4">
      <Name>是否冲红成功</Name>
      <Keyword>CHECK</Keyword>
      <DataList>PPC027check</DataList>
      <TargetDataList>PPC027</TargetDataList>
    </Step>
    <Step id = "5">
      <Name>发票查询</Name>
      <Keyword>IDETAIL</Keyword>
      <DataList>PPH027</DataList>
      <TargetProject>CLOUD</TargetProject>
    </Step>
    <Step id = "6">
      <Name>是否查询成功</Name>
      <Keyword>CHECK</Keyword>
      <DataList>PPH027check</DataList>
      <TargetDataList>PPH027</TargetDataList>
    </Step>
    <Step id = "7">
      <Name>查询结果比对</Name>
      <Keyword>CHECK</Keyword>
      <DataList>PPG027check</DataList>
    </Step>
  </TestCase>

    <!--清单冲红-->
  <TestCase>
    <Bh>PPC028</Bh>
    <CaseName>全部冲红清单单税率发票-普通0税率发票 </CaseName>
    <CaseId>51bs-2411</CaseId>
    <Description>冲红编号为PPC028的发票</Description>
    <Step id = "1">
      <Name>发票冲红</Name>
      <Keyword>IISSUE</Keyword>
      <DataList>PPC028</DataList>
      <TargetProject>CLOUD</TargetProject>
    </Step>
    <Step id = "2">
      <Name>是否冲红成功</Name>
      <Keyword>CHECK</Keyword>
      <DataList>PPC028check</DataList>
      <TargetDataList>PPC028</TargetDataList>
    </Step>
    <Step id = "3">
      <Name>发票查询</Name>
      <Keyword>IDETAIL</Keyword>
      <DataList>PPH028</DataList>
      <TargetProject>CLOUD</TargetProject>
    </Step>
    <Step id = "4">
      <Name>是否查询成功</Name>
      <Keyword>CHECK</Keyword>
      <DataList>PPH028check</DataList>
      <TargetDataList>PPH028</TargetDataList>
    </Step>
    <Step id = "5">
      <Name>查询结果比对</Name>
      <Keyword>CHECK</Keyword>
      <DataList>PPG028check</DataList>
    </Step>
  </TestCase>
    <TestCase>
    <Bh>PPC029</Bh>
    <CaseName>全部冲红清单单税率发票-免税税率发票 </CaseName>
    <CaseId>51bs-2411</CaseId>
    <Description>冲红编号为PPC029的发票</Description>
    <Step id = "1">
      <Name>发票冲红</Name>
      <Keyword>IISSUE</Keyword>
      <DataList>PPC029</DataList>
      <TargetProject>CLOUD</TargetProject>
    </Step>
    <Step id = "2">
      <Name>是否冲红成功</Name>
      <Keyword>CHECK</Keyword>
      <DataList>PPC029check</DataList>
      <TargetDataList>PPC029</TargetDataList>
    </Step>
    <Step id = "3">
      <Name>发票查询</Name>
      <Keyword>IDETAIL</Keyword>
      <DataList>PPH029</DataList>
      <TargetProject>CLOUD</TargetProject>
    </Step>
    <Step id = "4">
      <Name>是否查询成功</Name>
      <Keyword>CHECK</Keyword>
      <DataList>PPH029check</DataList>
      <TargetDataList>PPH029</TargetDataList>
    </Step>
    <Step id = "5">
      <Name>查询结果比对</Name>
      <Keyword>CHECK</Keyword>
      <DataList>PPG029check</DataList>
    </Step>
  </TestCase>
    <TestCase>
    <Bh>PPC030</Bh>
    <CaseName>全部冲红清单单税率发票-不征税税率发票 </CaseName>
    <CaseId>51bs-2411</CaseId>
    <Description>冲红编号为PPC030的发票</Description>
    <Step id = "1">
      <Name>发票冲红</Name>
      <Keyword>IISSUE</Keyword>
      <DataList>PPC030</DataList>
      <TargetProject>CLOUD</TargetProject>
    </Step>
    <Step id = "2">
      <Name>是否冲红成功</Name>
      <Keyword>CHECK</Keyword>
      <DataList>PPC030check</DataList>
      <TargetDataList>PPC030</TargetDataList>
    </Step>
    <Step id = "3">
      <Name>发票查询</Name>
      <Keyword>IDETAIL</Keyword>
      <DataList>PPH030</DataList>
      <TargetProject>CLOUD</TargetProject>
    </Step>
    <Step id = "4">
      <Name>是否查询成功</Name>
      <Keyword>CHECK</Keyword>
      <DataList>PPH030check</DataList>
      <TargetDataList>PPH030</TargetDataList>
    </Step>
    <Step id = "5">
      <Name>查询结果比对</Name>
      <Keyword>CHECK</Keyword>
      <DataList>PPG030check</DataList>
    </Step>
  </TestCase>

      <TestCase>
    <Bh>PPC031</Bh>
    <CaseName>全部冲红清单单税率发票-3%税率发票-含税冲红 </CaseName>
    <CaseId>51bs-2411</CaseId>
    <Description>冲红编号为PPC031的发票</Description>
    <Step id = "1">
      <Name>发票冲红</Name>
      <Keyword>IISSUE</Keyword>
      <DataList>PPC031</DataList>
      <TargetProject>CLOUD</TargetProject>
    </Step>
    <Step id = "2">
      <Name>是否冲红成功</Name>
      <Keyword>CHECK</Keyword>
      <DataList>PPC031check</DataList>
      <TargetDataList>PPC031</TargetDataList>
    </Step>
    <Step id = "3">
      <Name>发票查询</Name>
      <Keyword>IDETAIL</Keyword>
      <DataList>PPH031</DataList>
      <TargetProject>CLOUD</TargetProject>
    </Step>
    <Step id = "4">
      <Name>是否查询成功</Name>
      <Keyword>CHECK</Keyword>
      <DataList>PPH031check</DataList>
      <TargetDataList>PPH031</TargetDataList>
    </Step>
    <Step id = "5">
      <Name>查询结果比对</Name>
      <Keyword>CHECK</Keyword>
      <DataList>PPG031check</DataList>
    </Step>
  </TestCase>
  
   <TestCase>
    <Bh>PPC032</Bh>
    <CaseName>全部冲红清单单税率发票-5%税率发票 </CaseName>
    <CaseId>51bs-2411</CaseId>
    <Description>冲红编号为PPC032的发票</Description>
    <Step id = "1">
      <Name>发票冲红</Name>
      <Keyword>IISSUE</Keyword>
      <DataList>PPC032</DataList>
      <TargetProject>CLOUD</TargetProject>
    </Step>
    <Step id = "2">
      <Name>是否冲红成功</Name>
      <Keyword>CHECK</Keyword>
      <DataList>PPC032check</DataList>
      <TargetDataList>PPC032</TargetDataList>
    </Step>
    <Step id = "3">
      <Name>发票查询</Name>
      <Keyword>IDETAIL</Keyword>
      <DataList>PPH032</DataList>
      <TargetProject>CLOUD</TargetProject>
    </Step>
    <Step id = "4">
      <Name>是否查询成功</Name>
      <Keyword>CHECK</Keyword>
      <DataList>PPH032check</DataList>
      <TargetDataList>PPH032</TargetDataList>
    </Step>
    <Step id = "5">
      <Name>查询结果比对</Name>
      <Keyword>CHECK</Keyword>
      <DataList>PPG032check</DataList>
    </Step>
  </TestCase>
    <TestCase>
    <Bh>PPC033</Bh>
    <CaseName>全部冲红清单单税率发票-5%税率发票 </CaseName>
    <CaseId>51bs-2411</CaseId>
    <Description>冲红编号为PPC032的发票</Description>
    <Step id = "1">
      <Name>发票冲红</Name>
      <Keyword>IISSUE</Keyword>
      <DataList>PPC033</DataList>
      <TargetProject>CLOUD</TargetProject>
    </Step>
    <Step id = "2">
      <Name>是否冲红成功</Name>
      <Keyword>CHECK</Keyword>
      <DataList>PPCKJcheck</DataList>
      <TargetDataList>PPC033</TargetDataList>
    </Step>
    <Step id = "3">
      <Name>发票查询</Name>
      <Keyword>IDETAIL</Keyword>
      <DataList>PPH033</DataList>
      <TargetProject>CLOUD</TargetProject>
    </Step>
    <Step id = "4">
      <Name>是否查询成功</Name>
      <Keyword>CHECK</Keyword>
      <DataList>PPHCXcheck</DataList>
      <TargetDataList>PPH033</TargetDataList>
    </Step>
    <Step id = "5">
      <Name>查询结果比对</Name>
      <Keyword>CHECK</Keyword>
      <DataList>PPG033check</DataList>
    </Step>
  </TestCase>

  <TestCase>
    <Bh>PPC035</Bh>
    <CaseName>冲红清单多税率发票-0税率，免税，不征税率与普通税率组合 </CaseName>
    <CaseId>51bs-2411</CaseId>
    <Description>冲红编号为PPC035的发票</Description>
    <Step id = "1">
      <Name>发票冲红</Name>
      <Keyword>IISSUE</Keyword>
      <DataList>PPC035</DataList>
      <TargetProject>CLOUD</TargetProject>
    </Step>
    <Step id = "2">
      <Name>是否冲红成功</Name>
      <Keyword>CHECK</Keyword>
      <DataList>PPC035check</DataList>
      <TargetDataList>PPC035</TargetDataList>
    </Step>
    <Step id = "3">
      <Name>发票查询</Name>
      <Keyword>IDETAIL</Keyword>
      <DataList>PPH035</DataList>
      <TargetProject>CLOUD</TargetProject>
    </Step>
    <Step id = "4">
      <Name>是否查询成功</Name>
      <Keyword>CHECK</Keyword>
      <DataList>PPH035check</DataList>
      <TargetDataList>PPH035</TargetDataList>
    </Step>
    <Step id = "5">
      <Name>查询结果比对</Name>
      <Keyword>CHECK</Keyword>
      <DataList>PPG035check</DataList>
    </Step>
  </TestCase>

  <TestCase>
    <!--特殊冲红-->
    <Bh>PPC037</Bh>
    <CaseName>冲红不存在的12位发票代码、号码</CaseName>
    <CaseId>51bs-2408</CaseId>
    <Description>冲红编号为PPC037的发票</Description>
    <Step id = "1">
      <Name>发票冲红</Name>
      <Keyword>IISSUE</Keyword>
      <DataList>PPC037</DataList>
      <TargetProject>CLOUD</TargetProject>
    </Step>
    <Step id = "2">
      <Name>是否冲红成功</Name>
      <Keyword>CHECK</Keyword>
      <DataList>PPC037check</DataList>
      <TargetDataList>PPC037</TargetDataList>
    </Step>
    <Step id = "3">
      <Name>发票查询</Name>
      <Keyword>IDETAIL</Keyword>
      <DataList>PPH037</DataList>
      <TargetProject>CLOUD</TargetProject>
    </Step>
    <Step id = "4">
      <Name>是否查询成功</Name>
      <Keyword>CHECK</Keyword>
      <DataList>PPH037check</DataList>
      <TargetDataList>PPH037</TargetDataList>
    </Step>
    <Step id = "5">
      <Name>查询结果比对</Name>
      <Keyword>CHECK</Keyword>
      <DataList>PPG037check</DataList>
    </Step>
  </TestCase>

  <TestCase>
    <!--特殊冲红-->
    <Bh>PPC038</Bh>
    <CaseName>冲红不存在的10位发票代码、号码</CaseName>
    <CaseId>51bs-2408</CaseId>
    <Description>冲红编号为PPC038的发票</Description>
    <Step id = "1">
      <Name>发票冲红</Name>
      <Keyword>IISSUE</Keyword>
      <DataList>PPC038</DataList>
      <TargetProject>CLOUD</TargetProject>
    </Step>
    <Step id = "2">
      <Name>是否冲红成功</Name>
      <Keyword>CHECK</Keyword>
      <DataList>PPC038check</DataList>
      <TargetDataList>PPC038</TargetDataList>
    </Step>
    <Step id = "3">
      <Name>发票查询</Name>
      <Keyword>IDETAIL</Keyword>
      <DataList>PPH038</DataList>
      <TargetProject>CLOUD</TargetProject>
    </Step>
    <Step id = "4">
      <Name>是否查询成功</Name>
      <Keyword>CHECK</Keyword>
      <DataList>PPH038check</DataList>
      <TargetDataList>PPH038</TargetDataList>
    </Step>
    <Step id = "5">
      <Name>查询结果比对</Name>
      <Keyword>CHECK</Keyword>
      <DataList>PPG038check</DataList>
    </Step>
  </TestCase>

  <TestCase>
    <!--全部冲红-->
    <Bh>PPC039</Bh>
    <CaseName>全部冲红单税率单行发票- 普通0税率发票</CaseName>
    <CaseId>51bs-2411</CaseId>
    <Description>冲红编号为PPC039的发票</Description>
    <Step id = "1">
      <Name>发票冲红</Name>
      <Keyword>IISSUE</Keyword>
      <DataList>PPC039</DataList>
      <TargetProject>CLOUD</TargetProject>
    </Step>
    <Step id = "2">
      <Name>是否冲红成功</Name>
      <Keyword>CHECK</Keyword>
      <DataList>PPC039check</DataList>
      <TargetDataList>PPC039</TargetDataList>
    </Step>
    <Step id = "3">
      <Name>发票查询</Name>
      <Keyword>IDETAIL</Keyword>
      <DataList>PPH039</DataList>
      <TargetProject>CLOUD</TargetProject>
    </Step>
    <Step id = "4">
      <Name>是否查询成功</Name>
      <Keyword>CHECK</Keyword>
      <DataList>PPH039check</DataList>
      <TargetDataList>PPH039</TargetDataList>
    </Step>
    <Step id = "5">
      <Name>查询结果比对</Name>
      <Keyword>CHECK</Keyword>
      <DataList>PPG039check</DataList>
    </Step>
  </TestCase>

  <TestCase>
    <!--全部冲红-->
    <Bh>PPC040</Bh>
    <CaseName>全部冲红单税率单行发票- 免税税率发票</CaseName>
    <CaseId>51bs-2411</CaseId>
    <Description>冲红编号为PPC040的发票</Description>
    <Step id = "1">
      <Name>发票冲红</Name>
      <Keyword>IISSUE</Keyword>
      <DataList>PPC040</DataList>
      <TargetProject>CLOUD</TargetProject>
    </Step>
    <Step id = "2">
      <Name>是否冲红成功</Name>
      <Keyword>CHECK</Keyword>
      <DataList>PPC040check</DataList>
      <TargetDataList>PPC040</TargetDataList>
    </Step>
    <Step id = "3">
      <Name>发票查询</Name>
      <Keyword>IDETAIL</Keyword>
      <DataList>PPH040</DataList>
      <TargetProject>CLOUD</TargetProject>
    </Step>
    <Step id = "4">
      <Name>是否查询成功</Name>
      <Keyword>CHECK</Keyword>
      <DataList>PPH040check</DataList>
      <TargetDataList>PPH040</TargetDataList>
    </Step>
    <Step id = "5">
      <Name>查询结果比对</Name>
      <Keyword>CHECK</Keyword>
      <DataList>PPG040check</DataList>
    </Step>
  </TestCase>

  <TestCase>
    <!--全部冲红-->
    <Bh>PPC041</Bh>
    <CaseName>全部冲红单税率单行发票- 不征税税率发票</CaseName>
    <CaseId>51bs-2411</CaseId>
    <Description>冲红编号为PPC041的发票</Description>
    <Step id = "1">
      <Name>发票冲红</Name>
      <Keyword>IISSUE</Keyword>
      <DataList>PPC041</DataList>
      <TargetProject>CLOUD</TargetProject>
    </Step>
    <Step id = "2">
      <Name>是否冲红成功</Name>
      <Keyword>CHECK</Keyword>
      <DataList>PPC041check</DataList>
      <TargetDataList>PPC041</TargetDataList>
    </Step>
    <Step id = "3">
      <Name>发票查询</Name>
      <Keyword>IDETAIL</Keyword>
      <DataList>PPH041</DataList>
      <TargetProject>CLOUD</TargetProject>
    </Step>
    <Step id = "4">
      <Name>是否查询成功</Name>
      <Keyword>CHECK</Keyword>
      <DataList>PPH041check</DataList>
      <TargetDataList>PPH041</TargetDataList>
    </Step>
    <Step id = "5">
      <Name>查询结果比对</Name>
      <Keyword>CHECK</Keyword>
      <DataList>PPG041check</DataList>
    </Step>
  </TestCase>

  <TestCase>
    <!--全部冲红-->
    <Bh>PPC042</Bh>
    <CaseName>全部冲红单税率单行发票- 普通3%税率发票</CaseName>
    <CaseId>51bs-2411</CaseId>
    <Description>冲红编号为PPC042的发票</Description>
    <Step id = "1">
      <Name>发票冲红</Name>
      <Keyword>IISSUE</Keyword>
      <DataList>PPC042</DataList>
      <TargetProject>CLOUD</TargetProject>
    </Step>
    <Step id = "2">
      <Name>是否冲红成功</Name>
      <Keyword>CHECK</Keyword>
      <DataList>PPC042check</DataList>
      <TargetDataList>PPC042</TargetDataList>
    </Step>
    <Step id = "3">
      <Name>发票查询</Name>
      <Keyword>IDETAIL</Keyword>
      <DataList>PPH042</DataList>
      <TargetProject>CLOUD</TargetProject>
    </Step>
    <Step id = "4">
      <Name>是否查询成功</Name>
      <Keyword>CHECK</Keyword>
      <DataList>PPH042check</DataList>
      <TargetDataList>PPH042</TargetDataList>
    </Step>
    <Step id = "5">
      <Name>查询结果比对</Name>
      <Keyword>CHECK</Keyword>
      <DataList>PPG042check</DataList>
    </Step>
  </TestCase>

  <TestCase>
    <!--全部冲红-->
    <Bh>PPC043</Bh>
    <CaseName>全部冲红单税率3行发票- 普通0税率发票</CaseName>
    <CaseId>51bs-2411</CaseId>
    <Description>冲红编号为PPC043的发票</Description>
    <Step id = "1">
      <Name>发票冲红</Name>
      <Keyword>IISSUE</Keyword>
      <DataList>PPC043</DataList>
      <TargetProject>CLOUD</TargetProject>
    </Step>
    <Step id = "2">
      <Name>是否冲红成功</Name>
      <Keyword>CHECK</Keyword>
      <DataList>PPC043check</DataList>
      <TargetDataList>PPC043</TargetDataList>
    </Step>
    <Step id = "3">
      <Name>发票查询</Name>
      <Keyword>IDETAIL</Keyword>
      <DataList>PPH043</DataList>
      <TargetProject>CLOUD</TargetProject>
    </Step>
    <Step id = "4">
      <Name>是否查询成功</Name>
      <Keyword>CHECK</Keyword>
      <DataList>PPH043check</DataList>
      <TargetDataList>PPH043</TargetDataList>
    </Step>
    <Step id = "5">
      <Name>查询结果比对</Name>
      <Keyword>CHECK</Keyword>
      <DataList>PPG043check</DataList>
    </Step>
  </TestCase>

  <TestCase>
    <!--全部冲红-->
    <Bh>PPC044</Bh>
    <CaseName>全部冲红单税率3行发票- 免税税率发票</CaseName>
    <CaseId>51bs-2411</CaseId>
    <Description>冲红编号为PPC044的发票</Description>
    <Step id = "1">
      <Name>发票冲红</Name>
      <Keyword>IISSUE</Keyword>
      <DataList>PPC044</DataList>
      <TargetProject>CLOUD</TargetProject>
    </Step>
    <Step id = "2">
      <Name>是否冲红成功</Name>
      <Keyword>CHECK</Keyword>
      <DataList>PPC044check</DataList>
      <TargetDataList>PPC044</TargetDataList>
    </Step>
    <Step id = "3">
      <Name>发票查询</Name>
      <Keyword>IDETAIL</Keyword>
      <DataList>PPH044</DataList>
      <TargetProject>CLOUD</TargetProject>
    </Step>
    <Step id = "4">
      <Name>是否查询成功</Name>
      <Keyword>CHECK</Keyword>
      <DataList>PPH044check</DataList>
      <TargetDataList>PPH044</TargetDataList>
    </Step>
    <Step id = "5">
      <Name>查询结果比对</Name>
      <Keyword>CHECK</Keyword>
      <DataList>PPG044check</DataList>
    </Step>
  </TestCase>

  <TestCase>
    <!--全部冲红-->
    <Bh>PPC045</Bh>
    <CaseName>全部冲红单税率3行发票- 不征税税率发票</CaseName>
    <CaseId>51bs-2411</CaseId>
    <Description>冲红编号为PPC045的发票</Description>
    <Step id = "1">
      <Name>发票冲红</Name>
      <Keyword>IISSUE</Keyword>
      <DataList>PPC045</DataList>
      <TargetProject>CLOUD</TargetProject>
    </Step>
    <Step id = "2">
      <Name>是否冲红成功</Name>
      <Keyword>CHECK</Keyword>
      <DataList>PPC045check</DataList>
      <TargetDataList>PPC045</TargetDataList>
    </Step>
    <Step id = "3">
      <Name>发票查询</Name>
      <Keyword>IDETAIL</Keyword>
      <DataList>PPH045</DataList>
      <TargetProject>CLOUD</TargetProject>
    </Step>
    <Step id = "4">
      <Name>是否查询成功</Name>
      <Keyword>CHECK</Keyword>
      <DataList>PPH045check</DataList>
      <TargetDataList>PPH045</TargetDataList>
    </Step>
    <Step id = "5">
      <Name>查询结果比对</Name>
      <Keyword>CHECK</Keyword>
      <DataList>PPG045check</DataList>
    </Step>
  </TestCase>

  <TestCase>
    <!--全部冲红-->
    <Bh>PPC046</Bh>
    <CaseName>全部冲红单税率3行发票- 普通6%税率发票</CaseName>
    <CaseId>51bs-2411</CaseId>
    <Description>冲红编号为PPC046的发票</Description>
    <Step id = "1">
      <Name>发票冲红</Name>
      <Keyword>IISSUE</Keyword>
      <DataList>PPC046</DataList>
      <TargetProject>CLOUD</TargetProject>
    </Step>
    <Step id = "2">
      <Name>是否冲红成功</Name>
      <Keyword>CHECK</Keyword>
      <DataList>PPC046check</DataList>
      <TargetDataList>PPC046</TargetDataList>
    </Step>
    <Step id = "3">
      <Name>发票查询</Name>
      <Keyword>IDETAIL</Keyword>
      <DataList>PPH046</DataList>
      <TargetProject>CLOUD</TargetProject>
    </Step>
    <Step id = "4">
      <Name>是否查询成功</Name>
      <Keyword>CHECK</Keyword>
      <DataList>PPH046check</DataList>
      <TargetDataList>PPH046</TargetDataList>
    </Step>
    <Step id = "5">
      <Name>查询结果比对</Name>
      <Keyword>CHECK</Keyword>
      <DataList>PPG046check</DataList>
    </Step>
  </TestCase>

  <TestCase>
    <!--全部冲红-->
    <Bh>PPC047</Bh>
    <CaseName>全部冲红单税率3行发票- 11%-13%-17%税率发票</CaseName>
    <CaseId>51bs-2411</CaseId>
    <Description>冲红编号为PPC047的发票</Description>
    <Step id = "1">
      <Name>发票冲红</Name>
      <Keyword>IISSUE</Keyword>
      <DataList>PPC047</DataList>
      <TargetProject>CLOUD</TargetProject>
    </Step>
    <Step id = "2">
      <Name>是否冲红成功</Name>
      <Keyword>CHECK</Keyword>
      <DataList>PPC047check</DataList>
      <TargetDataList>PPC047</TargetDataList>
    </Step>
    <Step id = "3">
      <Name>发票查询</Name>
      <Keyword>IDETAIL</Keyword>
      <DataList>PPH047</DataList>
      <TargetProject>CLOUD</TargetProject>
    </Step>
    <Step id = "4">
      <Name>是否查询成功</Name>
      <Keyword>CHECK</Keyword>
      <DataList>PPH047check</DataList>
      <TargetDataList>PPH047</TargetDataList>
    </Step>
    <Step id = "5">
      <Name>查询结果比对</Name>
      <Keyword>CHECK</Keyword>
      <DataList>PPG047check</DataList>
    </Step>
  </TestCase>

  <TestCase>
    <!--全部冲红-->
    <Bh>PPC048</Bh>
    <CaseName>全部冲红非清单单税率8行发票- 普通0税率发票</CaseName>
    <CaseId>51bs-2411</CaseId>
    <Description>冲红编号为PPC048的发票</Description>
    <Step id = "1">
      <Name>发票冲红</Name>
      <Keyword>IISSUE</Keyword>
      <DataList>PPC048</DataList>
      <TargetProject>CLOUD</TargetProject>
    </Step>
    <Step id = "2">
      <Name>是否冲红成功</Name>
      <Keyword>CHECK</Keyword>
      <DataList>PPC048check</DataList>
      <TargetDataList>PPC048</TargetDataList>
    </Step>
    <Step id = "3">
      <Name>发票查询</Name>
      <Keyword>IDETAIL</Keyword>
      <DataList>PPH048</DataList>
      <TargetProject>CLOUD</TargetProject>
    </Step>
    <Step id = "4">
      <Name>是否查询成功</Name>
      <Keyword>CHECK</Keyword>
      <DataList>PPH048check</DataList>
      <TargetDataList>PPH048</TargetDataList>
    </Step>
    <Step id = "5">
      <Name>查询结果比对</Name>
      <Keyword>CHECK</Keyword>
      <DataList>PPG048check</DataList>
    </Step>
  </TestCase>

  <TestCase>
    <!--全部冲红-->
    <Bh>PPC049</Bh>
    <CaseName>全部冲红非清单单税率8行发票- 免税税率发票</CaseName>
    <CaseId>51bs-2411</CaseId>
    <Description>冲红编号为PPC049的发票</Description>
    <Step id = "1">
      <Name>发票冲红</Name>
      <Keyword>IISSUE</Keyword>
      <DataList>PPC049</DataList>
      <TargetProject>CLOUD</TargetProject>
    </Step>
    <Step id = "2">
      <Name>是否冲红成功</Name>
      <Keyword>CHECK</Keyword>
      <DataList>PPC049check</DataList>
      <TargetDataList>PPC049</TargetDataList>
    </Step>
    <Step id = "3">
      <Name>发票查询</Name>
      <Keyword>IDETAIL</Keyword>
      <DataList>PPH049</DataList>
      <TargetProject>CLOUD</TargetProject>
    </Step>
    <Step id = "4">
      <Name>是否查询成功</Name>
      <Keyword>CHECK</Keyword>
      <DataList>PPH049check</DataList>
      <TargetDataList>PPH049</TargetDataList>
    </Step>
    <Step id = "5">
      <Name>查询结果比对</Name>
      <Keyword>CHECK</Keyword>
      <DataList>PPG049check</DataList>
    </Step>
  </TestCase>

  <TestCase>
    <!--全部冲红-->
    <Bh>PPC050</Bh>
    <CaseName>全部冲红非清单单税率8行发票- 不征税税率发票</CaseName>
    <CaseId>51bs-2411</CaseId>
    <Description>冲红编号为PPC050的发票</Description>
    <Step id = "1">
      <Name>发票冲红</Name>
      <Keyword>IISSUE</Keyword>
      <DataList>PPC050</DataList>
      <TargetProject>CLOUD</TargetProject>
    </Step>
    <Step id = "2">
      <Name>是否冲红成功</Name>
      <Keyword>CHECK</Keyword>
      <DataList>PPC050check</DataList>
      <TargetDataList>PPC050</TargetDataList>
    </Step>
    <Step id = "3">
      <Name>发票查询</Name>
      <Keyword>IDETAIL</Keyword>
      <DataList>PPH050</DataList>
      <TargetProject>CLOUD</TargetProject>
    </Step>
    <Step id = "4">
      <Name>是否查询成功</Name>
      <Keyword>CHECK</Keyword>
      <DataList>PPH050check</DataList>
      <TargetDataList>PPH050</TargetDataList>
    </Step>
    <Step id = "5">
      <Name>查询结果比对</Name>
      <Keyword>CHECK</Keyword>
      <DataList>PPG050check</DataList>
    </Step>
  </TestCase>

  <TestCase>
    <!--全部冲红-->
    <Bh>PPC051</Bh>
    <CaseName>全部冲红非清单单税率8行发票- 普通3%税率发票</CaseName>
    <CaseId>51bs-2411</CaseId>
    <Description>冲红编号为PPC051的发票</Description>
    <Step id = "1">
      <Name>发票冲红</Name>
      <Keyword>IISSUE</Keyword>
      <DataList>PPC051</DataList>
      <TargetProject>CLOUD</TargetProject>
    </Step>
    <Step id = "2">
      <Name>是否冲红成功</Name>
      <Keyword>CHECK</Keyword>
      <DataList>PPC051check</DataList>
      <TargetDataList>PPC051</TargetDataList>
    </Step>
    <Step id = "3">
      <Name>发票查询</Name>
      <Keyword>IDETAIL</Keyword>
      <DataList>PPH051</DataList>
      <TargetProject>CLOUD</TargetProject>
    </Step>
    <Step id = "4">
      <Name>是否查询成功</Name>
      <Keyword>CHECK</Keyword>
      <DataList>PPH051check</DataList>
      <TargetDataList>PPH051</TargetDataList>
    </Step>
    <Step id = "5">
      <Name>查询结果比对</Name>
      <Keyword>CHECK</Keyword>
      <DataList>PPG051check</DataList>
    </Step>
  </TestCase>

  <TestCase>
    <!--全部冲红-->
    <Bh>PPC052</Bh>
    <CaseName>全部冲红非清单多税率8行发票- 0税率与普通税率发票</CaseName>
    <CaseId>51bs-2411</CaseId>
    <Description>冲红编号为PPC052的发票</Description>
    <Step id = "1">
      <Name>发票冲红</Name>
      <Keyword>IISSUE</Keyword>
      <DataList>PPC052</DataList>
      <TargetProject>CLOUD</TargetProject>
    </Step>
    <Step id = "2">
      <Name>是否冲红成功</Name>
      <Keyword>CHECK</Keyword>
      <DataList>PPC052check</DataList>
      <TargetDataList>PPC052</TargetDataList>
    </Step>
    <Step id = "3">
      <Name>发票查询</Name>
      <Keyword>IDETAIL</Keyword>
      <DataList>PPH052</DataList>
      <TargetProject>CLOUD</TargetProject>
    </Step>
    <Step id = "4">
      <Name>是否查询成功</Name>
      <Keyword>CHECK</Keyword>
      <DataList>PPH052check</DataList>
      <TargetDataList>PPH052</TargetDataList>
    </Step>
    <Step id = "5">
      <Name>查询结果比对</Name>
      <Keyword>CHECK</Keyword>
      <DataList>PPG052check</DataList>
    </Step>
  </TestCase>

  <TestCase>
    <!--全部冲红-->
    <Bh>PPC053</Bh>
    <CaseName>全部冲红非清单多税率8行发票- 免税税率与普通税率发票</CaseName>
    <CaseId>51bs-2411</CaseId>
    <Description>冲红编号为PPC053的发票</Description>
    <Step id = "1">
      <Name>发票冲红</Name>
      <Keyword>IISSUE</Keyword>
      <DataList>PPC053</DataList>
      <TargetProject>CLOUD</TargetProject>
    </Step>
    <Step id = "2">
      <Name>是否冲红成功</Name>
      <Keyword>CHECK</Keyword>
      <DataList>PPC053check</DataList>
      <TargetDataList>PPC053</TargetDataList>
    </Step>
    <Step id = "3">
      <Name>发票查询</Name>
      <Keyword>IDETAIL</Keyword>
      <DataList>PPH053</DataList>
      <TargetProject>CLOUD</TargetProject>
    </Step>
    <Step id = "4">
      <Name>是否查询成功</Name>
      <Keyword>CHECK</Keyword>
      <DataList>PPH053check</DataList>
      <TargetDataList>PPH053</TargetDataList>
    </Step>
    <Step id = "5">
      <Name>查询结果比对</Name>
      <Keyword>CHECK</Keyword>
      <DataList>PPG053check</DataList>
    </Step>
  </TestCase>

  <TestCase>
    <!--全部冲红-->
    <Bh>PPC054</Bh>
    <CaseName>全部冲红非清单多税率8行发票- 不征税与普通税率发票</CaseName>
    <CaseId>51bs-2411</CaseId>
    <Description>冲红编号为PPC054的发票</Description>
    <Step id = "1">
      <Name>发票冲红</Name>
      <Keyword>IISSUE</Keyword>
      <DataList>PPC054</DataList>
      <TargetProject>CLOUD</TargetProject>
    </Step>
    <Step id = "2">
      <Name>是否冲红成功</Name>
      <Keyword>CHECK</Keyword>
      <DataList>PPC054check</DataList>
      <TargetDataList>PPC054</TargetDataList>
    </Step>
    <Step id = "3">
      <Name>发票查询</Name>
      <Keyword>IDETAIL</Keyword>
      <DataList>PPH054</DataList>
      <TargetProject>CLOUD</TargetProject>
    </Step>
    <Step id = "4">
      <Name>是否查询成功</Name>
      <Keyword>CHECK</Keyword>
      <DataList>PPH054check</DataList>
      <TargetDataList>PPH054</TargetDataList>
    </Step>
    <Step id = "5">
      <Name>查询结果比对</Name>
      <Keyword>CHECK</Keyword>
      <DataList>PPG054check</DataList>
    </Step>
  </TestCase>
    
  <TestCase>
    <Bh>PPC055</Bh>
    <CaseName>冲红数量为0，冲红失败</CaseName>
      <CaseId>51bs-2413</CaseId>
    <Description>冲红编号为PPC055的发票</Description>
    <Step id = "1">
      <Name>开票</Name>
      <Keyword>IISSUE</Keyword>
      <DataList>PPV001</DataList>
      <TargetProject>CLOUD</TargetProject>
    </Step>
    <Step id = "2">
      <Name>是否开具成功</Name>
      <Keyword>CHECK</Keyword>
      <DataList>PPV001check</DataList>
      <TargetProject>CLOUD</TargetProject>
    </Step>
    <Step id = "3">
      <Name>发票冲红</Name>
      <Keyword>IISSUE</Keyword>
      <DataList>PPC055</DataList>
      <TargetProject>CLOUD</TargetProject>
    </Step>
    <Step id = "4">
      <Name>是否冲红成功</Name>
      <Keyword>CHECK</Keyword>
      <DataList>PPC055check</DataList>
      <TargetDataList>PPC055</TargetDataList>
    </Step>
  </TestCase>

  <TestCase>
    <Bh>PPC056</Bh>
    <CaseName>冲红数量为正数，冲红失败</CaseName>
      <CaseId>51bs-2413</CaseId>
    <Description>冲红编号为PPC056的发票</Description>
    <Step id = "1">
      <Name>开票</Name>
      <Keyword>IISSUE</Keyword>
      <DataList>PPV001</DataList>
      <TargetProject>CLOUD</TargetProject>
    </Step>
    <Step id = "2">
      <Name>是否开具成功</Name>
      <Keyword>CHECK</Keyword>
      <DataList>PPV001check</DataList>
      <TargetProject>CLOUD</TargetProject>
    </Step>
    <Step id = "3">
      <Name>发票冲红</Name>
      <Keyword>IISSUE</Keyword>
      <DataList>PPC056</DataList>
      <TargetProject>CLOUD</TargetProject>
    </Step>
    <Step id = "4">
      <Name>是否冲红成功</Name>
      <Keyword>CHECK</Keyword>
      <DataList>PPC056check</DataList>
      <TargetDataList>PPC056</TargetDataList>
    </Step>
  </TestCase>
  
  <TestCase>
    <Bh>PPC057</Bh>
    <CaseName>冲红数量为空，冲红失败</CaseName>
      <CaseId>51bs-2413</CaseId>
    <Description>冲红编号为PPC057的发票</Description>
    <Step id = "1">
      <Name>开票</Name>
      <Keyword>IISSUE</Keyword>
      <DataList>PPV001</DataList>
      <TargetProject>CLOUD</TargetProject>
    </Step>
    <Step id = "2">
      <Name>是否开具成功</Name>
      <Keyword>CHECK</Keyword>
      <DataList>PPV001check</DataList>
      <TargetProject>CLOUD</TargetProject>
    </Step>
    <Step id = "3">
      <Name>发票冲红</Name>
      <Keyword>IISSUE</Keyword>
      <DataList>PPC057</DataList>
      <TargetProject>CLOUD</TargetProject>
    </Step>
    <Step id = "4">
      <Name>是否冲红成功</Name>
      <Keyword>CHECK</Keyword>
      <DataList>PPC057check</DataList>
      <TargetDataList>PPC057</TargetDataList>
    </Step>
  </TestCase>
  
  <TestCase>
    <Bh>PPC058</Bh>
    <CaseName>冲红数量为负数，冲红成功</CaseName>
      <CaseId>51bs-2413</CaseId>
    <Description>冲红编号为PPC058的发票</Description>
    <Step id = "1">
      <Name>开票</Name>
      <Keyword>IISSUE</Keyword>
      <DataList>PPV001</DataList>
      <TargetProject>CLOUD</TargetProject>
    </Step>
    <Step id = "2">
      <Name>是否开具成功</Name>
      <Keyword>CHECK</Keyword>
      <DataList>PPV001check</DataList>
      <TargetProject>CLOUD</TargetProject>
    </Step>
    <Step id = "3">
      <Name>发票冲红</Name>
      <Keyword>IISSUE</Keyword>
      <DataList>PPC058</DataList>
      <TargetProject>CLOUD</TargetProject>
    </Step>
    <Step id = "4">
      <Name>是否冲红成功</Name>
      <Keyword>CHECK</Keyword>
      <DataList>PPC058check</DataList>
      <TargetDataList>PPC058</TargetDataList>
    </Step>
  </TestCase>
  
  <TestCase>
    <Bh>PPC059</Bh>
    <CaseName>冲红数量为中文、字母、特殊字符组合，冲红失败</CaseName>
      <CaseId>51bs-2413</CaseId>
    <Description>冲红编号为PPC059的发票</Description>
    <Step id = "1">
      <Name>开票</Name>
      <Keyword>IISSUE</Keyword>
      <DataList>PPV001</DataList>
      <TargetProject>CLOUD</TargetProject>
    </Step>
    <Step id = "2">
      <Name>是否开具成功</Name>
      <Keyword>CHECK</Keyword>
      <DataList>PPV001check</DataList>
      <TargetProject>CLOUD</TargetProject>
    </Step>
    <Step id = "3">
      <Name>发票冲红</Name>
      <Keyword>IISSUE</Keyword>
      <DataList>PPC059</DataList>
      <TargetProject>CLOUD</TargetProject>
    </Step>
    <Step id = "4">
      <Name>是否冲红成功</Name>
      <Keyword>CHECK</Keyword>
      <DataList>PPC059check</DataList>
      <TargetDataList>PPC059</TargetDataList>
    </Step>
  </TestCase>
  
   <TestCase>
    <Bh>PPC060</Bh>
    <CaseName>冲红数量长度整数位为17位，冲红失败（整数位最大支持16位)</CaseName>
      <CaseId>51bs-2413</CaseId>
    <Description>冲红编号为PPC060的发票</Description>
    <Step id = "1">
      <Name>开票</Name>
      <Keyword>IISSUE</Keyword>
      <DataList>PPV001</DataList>
      <TargetProject>CLOUD</TargetProject>
    </Step>
    <Step id = "2">
      <Name>是否开具成功</Name>
      <Keyword>CHECK</Keyword>
      <DataList>PPV001check</DataList>
      <TargetProject>CLOUD</TargetProject>
    </Step>
    <Step id = "3">
      <Name>发票冲红</Name>
      <Keyword>IISSUE</Keyword>
      <DataList>PPC060</DataList>
      <TargetProject>CLOUD</TargetProject>
    </Step>
    <Step id = "4">
      <Name>是否冲红成功</Name>
      <Keyword>CHECK</Keyword>
      <DataList>PPC060check</DataList>
      <TargetDataList>PPC060</TargetDataList>
    </Step>
  </TestCase>
  
  <TestCase>
    <Bh>PPC061</Bh>
    <CaseName>冲红数量长度小数位为9位，冲红成功（小数位最大保留8位，四舍五入)</CaseName>
      <CaseId>51bs-2413</CaseId>
    <Description>冲红编号为PPC061的发票</Description>
    <Step id = "1">
      <Name>开票</Name>
      <Keyword>IISSUE</Keyword>
      <DataList>PPV001</DataList>
      <TargetProject>CLOUD</TargetProject>
    </Step>
    <Step id = "2">
      <Name>是否开具成功</Name>
      <Keyword>CHECK</Keyword>
      <DataList>PPV001check</DataList>
      <TargetProject>CLOUD</TargetProject>
    </Step>
    <Step id = "3">
      <Name>发票冲红</Name>
      <Keyword>IISSUE</Keyword>
      <DataList>PPC061</DataList>
      <TargetProject>CLOUD</TargetProject>
    </Step>
    <Step id = "4">
      <Name>是否冲红成功</Name>
      <Keyword>CHECK</Keyword>
      <DataList>PPC061check</DataList>
      <TargetDataList>PPC061</TargetDataList>
    </Step>
  </TestCase>


</Data>